odoo/addons/account_portal_invoice_search_by_lot/README.rst
odoo/addons/account_portal_invoice_search_by_lot/__init__.py
odoo/addons/account_portal_invoice_search_by_lot/__manifest__.py
odoo/addons/account_portal_invoice_search_by_lot/i18n/account_portal_invoice_search_by_lot.pot
odoo/addons/account_portal_invoice_search_by_lot/i18n/es.po
odoo/addons/account_portal_invoice_search_by_lot/models/__init__.py
odoo/addons/account_portal_invoice_search_by_lot/models/account_move.py
odoo/addons/account_portal_invoice_search_by_lot/readme/CONTRIBUTORS.rst
odoo/addons/account_portal_invoice_search_by_lot/readme/DESCRIPTION.rst
odoo/addons/account_portal_invoice_search_by_lot/readme/USAGE.rst
odoo/addons/account_portal_invoice_search_by_lot/static/description/icon.png
odoo/addons/account_portal_invoice_search_by_lot/static/description/index.html
odoo13_addon_account_portal_invoice_search_by_lot-13.0.1.0.1.dev2.dist-info/METADATA
odoo13_addon_account_portal_invoice_search_by_lot-13.0.1.0.1.dev2.dist-info/WHEEL
odoo13_addon_account_portal_invoice_search_by_lot-13.0.1.0.1.dev2.dist-info/top_level.txt
odoo13_addon_account_portal_invoice_search_by_lot-13.0.1.0.1.dev2.dist-info/RECORD
