Metadata-Version: 2.1
Name: odoo13-addon-account_portal_invoice_search_by_lot
Version: 13.0.1.0.1.dev2
Summary: Account Portal Invoice Search By Lot
Home-page: https://github.com/OCA/account-invoicing
Author: Tecnativa, Odoo Community Association (OCA)
Author-email: support@odoo-community.org
License: AGPL-3
Classifier: Programming Language :: Python
Classifier: Framework :: Odoo
Classifier: Framework :: Odoo :: 13.0
Classifier: License :: OSI Approved :: GNU Affero General Public License v3
Classifier: Development Status :: 4 - Beta
Requires-Python: >=3.5
Requires-Dist: odoo13-addon-account-portal-invoice-search
Requires-Dist: odoo <13.1dev,>=13.0a
